titanic_utils/__init__.py
titanic_utils/utils.py
nickscoolproject2342-0.0.1.dist-info/METADATA
nickscoolproject2342-0.0.1.dist-info/WHEEL
nickscoolproject2342-0.0.1.dist-info/top_level.txt
nickscoolproject2342-0.0.1.dist-info/RECORD
