Metadata-Version: 2.1
Name: nickscoolproject2342
Version: 0.0.1
Summary: Lovely Spam! Wonderful Spam!
Requires-Python: >=3.6
Requires-Dist: requests
Requires-Dist: pandas
Requires-Dist: matplotlib
Requires-Dist: seaborn
Requires-Dist: jupyterlab
Requires-Dist: ipykernel
